{
  "content": "# Note 5 - 2/3/2026\n\n5️⃣\nIf a tool gives people more control,\nit will always attract fewer users at first.\n\nFreedom scales after conviction —\nnot before.\n\n“For you were called to freedom… only do not use your freedom as an opportunity for the flesh.” — Galatians 5:13\n\n#freedom #sovereigntech #nostr",
  "created_at": 1770168197,
  "id": "6293006a1664de8b51c698ef9db28d8ca4235eeba805bda801f40bfeb98c9b0e",
  "kind": 1,
  "pubkey": "2b998b04e2a1fe6855b2e0ab10bb92b774b5dfa0f78926c7a65ae08086727e47",
  "sig": "41e224f86475b6ab6d7c1d223ee65e92237c13c86e04bed7ed0c86c7f17c24af7ece0a6c438d795cf36567bd1e44c5f178c07d4ad982bf71093d029c0d0a8fee",
  "tags": [
    [
      "d",
      "note-5-232026-1770168197"
    ],
    [
      "title",
      "Note 5 - 2/3/2026"
    ],
    [
      "published_at",
      "1770168197"
    ],
    [
      "client",
      "Continuum-Pro-localhost"
    ],
    [
      "t",
      "freedom"
    ],
    [
      "t",
      "sovereigntech"
    ],
    [
      "t",
      "nostr"
    ]
  ]
}